joplin/__init__.py
joplin/joplin_api.py
joplin/joplin_utils.py
joplin/test.py
mseep_joplin_mcp-0.1.3.dist-info/METADATA
mseep_joplin_mcp-0.1.3.dist-info/WHEEL
mseep_joplin_mcp-0.1.3.dist-info/licenses/LICENSE
mseep_joplin_mcp-0.1.3.dist-info/RECORD
