Metadata-Version: 2.4
Name: mseep-joplin-mcp
Version: 0.1.3
Summary: Joplin MCP Server - A Model Context Protocol Server for Joplin
Author-email: mseep <support@skydeck.ai>
License-Expression: MIT
License-File: LICENSE
Keywords: ai,claude,joplin,mcp,note-taking
Requires-Python: >=3.10
Requires-Dist: httpx
Requires-Dist: mcp[cli]
Requires-Dist: pydantic
Requires-Dist: python-dotenv
Requires-Dist: requests
Provides-Extra: dev
Requires-Dist: black>=24.1.1; extra == 'dev'
Requires-Dist: mypy>=1.8.0; extra == 'dev'
Requires-Dist: pytest-cov>=4.1.0; extra == 'dev'
Requires-Dist: pytest>=8.0.0; extra == 'dev'
